MANIFEST.in
README.rst
VERSION.txt
pyproject.toml
pyproject.toml.m4
requirements.txt
setup.py
tox.ini
passagemath_docbuild.egg-info/PKG-INFO
passagemath_docbuild.egg-info/SOURCES.txt
passagemath_docbuild.egg-info/dependency_links.txt
passagemath_docbuild.egg-info/requires.txt
passagemath_docbuild.egg-info/top_level.txt
sage_docbuild/__init__.py
sage_docbuild/__main__.py
sage_docbuild/build_options.py
sage_docbuild/builders.py
sage_docbuild/conf.py
sage_docbuild/sphinxbuild.py
sage_docbuild/utils.py
sage_docbuild/vendor.py
sage_docbuild/ext/__init__.py
sage_docbuild/ext/inventory_builder.py
sage_docbuild/ext/multidocs.py
sage_docbuild/ext/sage_autodoc.py